jefferson/__init__.py
jefferson/cli.py
jefferson/compression/__init__.py
jefferson/compression/jffs2_lzma.py
jefferson/compression/rtime.py
jefferson/core/__init__.py
jefferson/jffs2.py
jefferson-0.4.5.dist-info/LICENSE
jefferson-0.4.5.dist-info/METADATA
jefferson-0.4.5.dist-info/WHEEL
jefferson-0.4.5.dist-info/entry_points.txt
jefferson-0.4.5.dist-info/RECORD
