Metadata-Version: 2.1
Name: jefferson
Version: 0.4.5
Summary: JFFS2 filesystem extraction tool.
License: MIT
Author: ONEKEY
Author-email: support@onekey.com
Requires-Python: >=3.8,<4.0
Classifier: License :: OSI Approved :: MIT License
Classifier: Programming Language :: Python :: 3
Classifier: Programming Language :: Python :: 3.8
Classifier: Programming Language :: Python :: 3.9
Classifier: Programming Language :: Python :: 3.10
Classifier: Programming Language :: Python :: 3.11
Requires-Dist: click (>=8.1.3,<9.0.0)
Requires-Dist: cstruct (>=5.2,<6.0)
Requires-Dist: lzallright (>=0.2.1,<0.3.0)
